{"timestamp": "2025-05-01 10:51:20", "raw_analysis": "### Vehicle Type:\nThe car in the image appears to be a **Ford Mustang**, identifiable by its coupe design, window shape, and distinctive styling features.\n\n---\n\n### Damage Analysis:\n\n#### 1. Type of Damage:\n- **Dent:** The most prominent damage is a large dent on the rear quarter panel (near the rear wheel). The metal is visibly deformed and creased.\n- **Scratch:** There are visible scratches across the affected area, likely caused by impact or friction.\n- **Misalignment/Deformation:** The lower trim and body panel near the side skirt appear to be misaligned or deformed due to the impact.\n- **Possible Internal Damage:** The structural integrity around the wheel arch may be compromised. Internal components (e.g., suspension or rear axle) could be affected, though not visibly confirmed in this image.\n\n#### 2. Severity of Damage:\n- **Moderate to Severe:** The dent and deformation of the rear quarter panel are significant, which may require panel replacement rather than repair. Scratches are secondary but add to the overall damage severity. Possible internal damage elevates the severity.\n\n#### 3. Affected Areas:\n- **Rear Quarter Panel (Driver Side):** This is the primary area of damage.\n- **Side Skirt:** Deformed and misaligned near the bottom of the quarter panel.\n- **Rear Wheel Area:** No visible damage to the wheel or tire, but there is potential internal damage to the suspension or axle that would need further inspection.\n\n---\n\n### Cost Estimation (Netherlands-Based Insurance Company):\n1. **Panel Replacement:**  \n   - Rear quarter panel replacement: \u20ac1,000 - \u20ac1,500.  \n   - Labor costs for fitting, painting, and blending the new panel: \u20ac1,000 - \u20ac1,500.  \n\n2. **Side Skirt Repair/Replacement:**  \n   - Repair or replace side skirt: \u20ac300 - \u20ac600.  \n\n3. **Scratch Removal/Paint Correction:**  \n   - Paint blending and correction: \u20ac500 - \u20ac800.  \n\n4. **Internal Damage Inspection:**  \n   - Suspension and axle inspection with potential repairs: \u20ac300 - \u20ac1,000 (if required).  \n\n**Total Estimated Cost:** \u20ac2,800 - \u20ac5,400.\n\n---\n\n### Fraud Analysis:\n\n#### Likelihood of Fraud: **Low**\n**Reasoning:**\n- The damage appears consistent with a side-impact collision or scraping against a solid object (e.g., pole, barrier).\n- There are no signs of photo manipulation or inconsistent lighting/shadows that would suggest tampering.\n- The dent pattern and scratches align realistically with physical impact behavior.\n- The car type (Ford Mustang) and damage location match typical accident scenarios for performance vehicles.\n\n---\n\n### Conclusion:\n- **Type of Damage:** Dent, scratch, deformation.\n- **Severity:** Moderate to severe.\n- **Affected Areas:** Rear quarter panel, side skirt, potential internal damage near rear wheel.\n- **Cost Estimate:** \u20ac2,800 - \u20ac5,400.\n- **Likelihood of Fraud:** Low (damage appears authentic).", "vehicle_type": "### Vehicle Type:", "damage_types": ["Dent", "Scratch", "Collision"], "fraud_likelihood": "Low", "cost_estimate": "### Cost Estimation (Netherlands-Based Insurance Company):", "severity": "Severe", "report_id": "20250501105120fc684c"}